{
  "pageId": "cu-overspending",
  "pageName": "CU Overspending",
  "fetchedAt": "2025-08-09T03:20:46.174Z",
  "charts": [
    {
      "success": true,
      "data": [
        {
          "partition_0": "2025-07-12",
          "overspent_fee_bucket": "10-30%",
          "txns": 16286568
        },
        {
          "partition_0": "2025-07-15",
          "overspent_fee_bucket": "80-100%",
          "txns": 36374366
        },
        {
          "partition_0": "2025-07-15",
          "overspent_fee_bucket": "50-80%",
          "txns": 22263249
        },
        {
          "partition_0": "2025-08-05",
          "overspent_fee_bucket": "0-10%",
          "txns": 640630
        },
        {
          "partition_0": "2025-07-17",
          "overspent_fee_bucket": "80-100%",
          "txns": 38680065
        },
        {
          "partition_0": "2025-07-09",
          "overspent_fee_bucket": "50-80%",
          "txns": 21230128
        },
        {
          "partition_0": "2025-07-30",
          "overspent_fee_bucket": "30-50%",
          "txns": 9847468
        },
        {
          "partition_0": "2025-07-29",
          "overspent_fee_bucket": "50-80%",
          "txns": 23978239
        },
        {
          "partition_0": "2025-07-30",
          "overspent_fee_bucket": "50-80%",
          "txns": 21782465
        },
        {
          "partition_0": "2025-07-28",
          "overspent_fee_bucket": "0%",
          "txns": 6080561
        },
        {
          "partition_0": "2025-08-04",
          "overspent_fee_bucket": "0-10%",
          "txns": 590788
        },
        {
          "partition_0": "2025-07-10",
          "overspent_fee_bucket": "10-30%",
          "txns": 15841184
        },
        {
          "partition_0": "2025-07-29",
          "overspent_fee_bucket": "0%",
          "txns": 6314341
        },
        {
          "partition_0": "2025-07-14",
          "overspent_fee_bucket": "0-10%",
          "txns": 10486350
        },
        {
          "partition_0": "2025-07-21",
          "overspent_fee_bucket": "80-100%",
          "txns": 39113482
        },
        {
          "partition_0": "2025-07-27",
          "overspent_fee_bucket": "0-10%",
          "txns": 8147705
        },
        {
          "partition_0": "2025-07-20",
          "overspent_fee_bucket": "0-10%",
          "txns": 9999966
        },
        {
          "partition_0": "2025-07-22",
          "overspent_fee_bucket": "30-50%",
          "txns": 11176777
        },
        {
          "partition_0": "2025-07-14",
          "overspent_fee_bucket": "50-80%",
          "txns": 22942822
        },
        {
          "partition_0": "2025-08-03",
          "overspent_fee_bucket": "30-50%",
          "txns": 1953063
        },
        {
          "partition_0": "2025-07-26",
          "overspent_fee_bucket": "10-30%",
          "txns": 15541775
        },
        {
          "partition_0": "2025-07-27",
          "overspent_fee_bucket": "50-80%",
          "txns": 20688122
        },
        {
          "partition_0": "2025-07-30",
          "overspent_fee_bucket": "0%",
          "txns": 6215653
        },
        {
          "partition_0": "2025-07-29",
          "overspent_fee_bucket": "10-30%",
          "txns": 17153573
        },
        {
          "partition_0": "2025-07-17",
          "overspent_fee_bucket": "10-30%",
          "txns": 19396129
        },
        {
          "partition_0": "2025-07-31",
          "overspent_fee_bucket": "80-100%",
          "txns": 39657551
        },
        {
          "partition_0": "2025-07-18",
          "overspent_fee_bucket": "0-10%",
          "txns": 11783257
        },
        {
          "partition_0": "2025-07-09",
          "overspent_fee_bucket": "0%",
          "txns": 3392554
        },
        {
          "partition_0": "2025-07-19",
          "overspent_fee_bucket": "0%",
          "txns": 3969426
        },
        {
          "partition_0": "2025-07-12",
          "overspent_fee_bucket": "50-80%",
          "txns": 18292087
        },
        {
          "partition_0": "2025-07-28",
          "overspent_fee_bucket": "0-10%",
          "txns": 9697510
        },
        {
          "partition_0": "2025-07-14",
          "overspent_fee_bucket": "0%",
          "txns": 4058913
        },
        {
          "partition_0": "2025-08-02",
          "overspent_fee_bucket": "80-100%",
          "txns": 32698128
        },
        {
          "partition_0": "2025-07-14",
          "overspent_fee_bucket": "30-50%",
          "txns": 10372504
        },
        {
          "partition_0": "2025-07-29",
          "overspent_fee_bucket": "0-10%",
          "txns": 9228673
        },
        {
          "partition_0": "2025-07-11",
          "overspent_fee_bucket": "80-100%",
          "txns": 39744521
        },
        {
          "partition_0": "2025-07-12",
          "overspent_fee_bucket": "0%",
          "txns": 3212384
        },
        {
          "partition_0": "2025-07-26",
          "overspent_fee_bucket": "0-10%",
          "txns": 7450021
        },
        {
          "partition_0": "2025-07-12",
          "overspent_fee_bucket": "30-50%",
          "txns": 9210406
        },
        {
          "partition_0": "2025-07-28",
          "overspent_fee_bucket": "80-100%",
          "txns": 39384730
        },
        {
          "partition_0": "2025-07-23",
          "overspent_fee_bucket": "0-10%",
          "txns": 11474048
        },
        {
          "partition_0": "2025-07-27",
          "overspent_fee_bucket": "0%",
          "txns": 3864681
        },
        {
          "partition_0": "2025-07-10",
          "overspent_fee_bucket": "0-10%",
          "txns": 9517279
        },
        {
          "partition_0": "2025-07-19",
          "overspent_fee_bucket": "50-80%",
          "txns": 18415944
        },
        {
          "partition_0": "2025-07-13",
          "overspent_fee_bucket": "80-100%",
          "txns": 38349792
        },
        {
          "partition_0": "2025-07-31",
          "overspent_fee_bucket": "10-30%",
          "txns": 17728592
        },
        {
          "partition_0": "2025-07-22",
          "overspent_fee_bucket": "80-100%",
          "txns": 39076257
        },
        {
          "partition_0": "2025-07-26",
          "overspent_fee_bucket": "50-80%",
          "txns": 21279652
        },
        {
          "partition_0": "2025-07-13",
          "overspent_fee_bucket": "30-50%",
          "txns": 8978491
        },
        {
          "partition_0": "2025-08-03",
          "overspent_fee_bucket": "50-80%",
          "txns": 6751469
        },
        {
          "partition_0": "2025-08-03",
          "overspent_fee_bucket": "80-100%",
          "txns": 11293217
        },
        {
          "partition_0": "2025-07-14",
          "overspent_fee_bucket": "10-30%",
          "txns": 17039970
        },
        {
          "partition_0": "2025-07-18",
          "overspent_fee_bucket": "30-50%",
          "txns": 10865760
        },
        {
          "partition_0": "2025-08-06",
          "overspent_fee_bucket": "30-50%",
          "txns": 2271848
        },
        {
          "partition_0": "2025-07-21",
          "overspent_fee_bucket": "10-30%",
          "txns": 18622863
        },
        {
          "partition_0": "2025-07-16",
          "overspent_fee_bucket": "30-50%",
          "txns": 10783457
        },
        {
          "partition_0": "2025-07-22",
          "overspent_fee_bucket": "50-80%",
          "txns": 20550415
        },
        {
          "partition_0": "2025-07-22",
          "overspent_fee_bucket": "0%",
          "txns": 6439512
        },
        {
          "partition_0": "2025-07-19",
          "overspent_fee_bucket": "80-100%",
          "txns": 34233646
        },
        {
          "partition_0": "2025-07-09",
          "overspent_fee_bucket": "30-50%",
          "txns": 8713141
        },
        {
          "partition_0": "2025-07-25",
          "overspent_fee_bucket": "50-80%",
          "txns": 24240392
        },
        {
          "partition_0": "2025-07-14",
          "overspent_fee_bucket": "80-100%",
          "txns": 37338185
        },
        {
          "partition_0": "2025-07-13",
          "overspent_fee_bucket": "50-80%",
          "txns": 19841199
        },
        {
          "partition_0": "2025-07-28",
          "overspent_fee_bucket": "50-80%",
          "txns": 26206602
        },
        {
          "partition_0": "2025-07-28",
          "overspent_fee_bucket": "30-50%",
          "txns": 10581489
        },
        {
          "partition_0": "2025-07-16",
          "overspent_fee_bucket": "10-30%",
          "txns": 18401325
        },
        {
          "partition_0": "2025-08-02",
          "overspent_fee_bucket": "10-30%",
          "txns": 17973119
        },
        {
          "partition_0": "2025-07-15",
          "overspent_fee_bucket": "30-50%",
          "txns": 10928999
        },
        {
          "partition_0": "2025-07-09",
          "overspent_fee_bucket": "10-30%",
          "txns": 15014110
        },
        {
          "partition_0": "2025-07-24",
          "overspent_fee_bucket": "30-50%",
          "txns": 10737041
        },
        {
          "partition_0": "2025-07-10",
          "overspent_fee_bucket": "80-100%",
          "txns": 43358997
        },
        {
          "partition_0": "2025-07-26",
          "overspent_fee_bucket": "0%",
          "txns": 3285460
        },
        {
          "partition_0": "2025-07-25",
          "overspent_fee_bucket": "10-30%",
          "txns": 16724680
        },
        {
          "partition_0": "2025-08-06",
          "overspent_fee_bucket": "0-10%",
          "txns": 521865
        },
        {
          "partition_0": "2025-07-21",
          "overspent_fee_bucket": "50-80%",
          "txns": 19878315
        },
        {
          "partition_0": "2025-07-29",
          "overspent_fee_bucket": "80-100%",
          "txns": 38864035
        },
        {
          "partition_0": "2025-07-23",
          "overspent_fee_bucket": "10-30%",
          "txns": 17661647
        },
        {
          "partition_0": "2025-07-30",
          "overspent_fee_bucket": "80-100%",
          "txns": 40009463
        },
        {
          "partition_0": "2025-07-21",
          "overspent_fee_bucket": "30-50%",
          "txns": 10240482
        },
        {
          "partition_0": "2025-08-01",
          "overspent_fee_bucket": "0-10%",
          "txns": 10176433
        },
        {
          "partition_0": "2025-07-13",
          "overspent_fee_bucket": "10-30%",
          "txns": 15996189
        },
        {
          "partition_0": "2025-07-21",
          "overspent_fee_bucket": "0-10%",
          "txns": 12041084
        },
        {
          "partition_0": "2025-07-19",
          "overspent_fee_bucket": "10-30%",
          "txns": 17769252
        },
        {
          "partition_0": "2025-08-04",
          "overspent_fee_bucket": "30-50%",
          "txns": 2573310
        },
        {
          "partition_0": "2025-08-02",
          "overspent_fee_bucket": "0-10%",
          "txns": 8124710
        },
        {
          "partition_0": "2025-07-25",
          "overspent_fee_bucket": "80-100%",
          "txns": 39220620
        },
        {
          "partition_0": "2025-07-20",
          "overspent_fee_bucket": "80-100%",
          "txns": 36334574
        },
        {
          "partition_0": "2025-08-05",
          "overspent_fee_bucket": "80-100%",
          "txns": 13438398
        },
        {
          "partition_0": "2025-08-03",
          "overspent_fee_bucket": "0%",
          "txns": 543660
        },
        {
          "partition_0": "2025-07-27",
          "overspent_fee_bucket": "30-50%",
          "txns": 8495589
        },
        {
          "partition_0": "2025-07-13",
          "overspent_fee_bucket": "0%",
          "txns": 3101986
        },
        {
          "partition_0": "2025-07-17",
          "overspent_fee_bucket": "0-10%",
          "txns": 12524512
        },
        {
          "partition_0": "2025-07-11",
          "overspent_fee_bucket": "0%",
          "txns": 4243874
        },
        {
          "partition_0": "2025-07-17",
          "overspent_fee_bucket": "30-50%",
          "txns": 11385079
        },
        {
          "partition_0": "2025-07-22",
          "overspent_fee_bucket": "10-30%",
          "txns": 19460481
        },
        {
          "partition_0": "2025-07-15",
          "overspent_fee_bucket": "10-30%",
          "txns": 18186921
        },
        {
          "partition_0": "2025-07-31",
          "overspent_fee_bucket": "0%",
          "txns": 5513281
        },
        {
          "partition_0": "2025-07-10",
          "overspent_fee_bucket": "50-80%",
          "txns": 21042272
        },
        {
          "partition_0": "2025-07-11",
          "overspent_fee_bucket": "50-80%",
          "txns": 20922698
        },
        {
          "partition_0": "2025-07-24",
          "overspent_fee_bucket": "0-10%",
          "txns": 11134828
        },
        {
          "partition_0": "2025-07-16",
          "overspent_fee_bucket": "80-100%",
          "txns": 38081482
        },
        {
          "partition_0": "2025-07-30",
          "overspent_fee_bucket": "10-30%",
          "txns": 17772010
        },
        {
          "partition_0": "2025-08-01",
          "overspent_fee_bucket": "10-30%",
          "txns": 18378337
        },
        {
          "partition_0": "2025-07-23",
          "overspent_fee_bucket": "80-100%",
          "txns": 39248586
        },
        {
          "partition_0": "2025-07-13",
          "overspent_fee_bucket": "0-10%",
          "txns": 8970684
        },
        {
          "partition_0": "2025-07-25",
          "overspent_fee_bucket": "0-10%",
          "txns": 10128778
        },
        {
          "partition_0": "2025-07-18",
          "overspent_fee_bucket": "50-80%",
          "txns": 21755704
        },
        {
          "partition_0": "2025-08-05",
          "overspent_fee_bucket": "50-80%",
          "txns": 6674271
        },
        {
          "partition_0": "2025-08-02",
          "overspent_fee_bucket": "0%",
          "txns": 5073933
        },
        {
          "partition_0": "2025-07-11",
          "overspent_fee_bucket": "10-30%",
          "txns": 17463226
        },
        {
          "partition_0": "2025-08-05",
          "overspent_fee_bucket": "30-50%",
          "txns": 2758460
        },
        {
          "partition_0": "2025-07-28",
          "overspent_fee_bucket": "10-30%",
          "txns": 17804773
        },
        {
          "partition_0": "2025-07-18",
          "overspent_fee_bucket": "80-100%",
          "txns": 39649615
        },
        {
          "partition_0": "2025-07-30",
          "overspent_fee_bucket": "0-10%",
          "txns": 9268999
        },
        {
          "partition_0": "2025-07-17",
          "overspent_fee_bucket": "0%",
          "txns": 5654598
        },
        {
          "partition_0": "2025-07-24",
          "overspent_fee_bucket": "80-100%",
          "txns": 41682118
        },
        {
          "partition_0": "2025-08-06",
          "overspent_fee_bucket": "50-80%",
          "txns": 5650964
        },
        {
          "partition_0": "2025-08-04",
          "overspent_fee_bucket": "50-80%",
          "txns": 7557371
        },
        {
          "partition_0": "2025-08-04",
          "overspent_fee_bucket": "80-100%",
          "txns": 13500977
        },
        {
          "partition_0": "2025-07-20",
          "overspent_fee_bucket": "10-30%",
          "txns": 18823393
        },
        {
          "partition_0": "2025-07-24",
          "overspent_fee_bucket": "50-80%",
          "txns": 23935499
        },
        {
          "partition_0": "2025-07-31",
          "overspent_fee_bucket": "50-80%",
          "txns": 19548530
        },
        {
          "partition_0": "2025-07-17",
          "overspent_fee_bucket": "50-80%",
          "txns": 22426541
        },
        {
          "partition_0": "2025-08-03",
          "overspent_fee_bucket": "0-10%",
          "txns": 374638
        },
        {
          "partition_0": "2025-07-11",
          "overspent_fee_bucket": "0-10%",
          "txns": 10913863
        },
        {
          "partition_0": "2025-08-05",
          "overspent_fee_bucket": "10-30%",
          "txns": 2845806
        },
        {
          "partition_0": "2025-07-16",
          "overspent_fee_bucket": "0%",
          "txns": 4623189
        },
        {
          "partition_0": "2025-08-06",
          "overspent_fee_bucket": "80-100%",
          "txns": 12093422
        },
        {
          "partition_0": "2025-08-01",
          "overspent_fee_bucket": "80-100%",
          "txns": 34371549
        },
        {
          "partition_0": "2025-07-23",
          "overspent_fee_bucket": "0%",
          "txns": 5529960
        },
        {
          "partition_0": "2025-08-01",
          "overspent_fee_bucket": "30-50%",
          "txns": 8855818
        },
        {
          "partition_0": "2025-07-10",
          "overspent_fee_bucket": "30-50%",
          "txns": 8395988
        },
        {
          "partition_0": "2025-07-10",
          "overspent_fee_bucket": "0%",
          "txns": 3612314
        },
        {
          "partition_0": "2025-07-09",
          "overspent_fee_bucket": "0-10%",
          "txns": 8550697
        },
        {
          "partition_0": "2025-07-19",
          "overspent_fee_bucket": "0-10%",
          "txns": 8964918
        },
        {
          "partition_0": "2025-08-01",
          "overspent_fee_bucket": "50-80%",
          "txns": 15775244
        },
        {
          "partition_0": "2025-07-12",
          "overspent_fee_bucket": "0-10%",
          "txns": 8978913
        },
        {
          "partition_0": "2025-07-11",
          "overspent_fee_bucket": "30-50%",
          "txns": 9771004
        },
        {
          "partition_0": "2025-07-09",
          "overspent_fee_bucket": "80-100%",
          "txns": 42675633
        },
        {
          "partition_0": "2025-07-31",
          "overspent_fee_bucket": "0-10%",
          "txns": 8807745
        },
        {
          "partition_0": "2025-07-21",
          "overspent_fee_bucket": "0%",
          "txns": 5413418
        },
        {
          "partition_0": "2025-07-27",
          "overspent_fee_bucket": "10-30%",
          "txns": 16546535
        },
        {
          "partition_0": "2025-07-15",
          "overspent_fee_bucket": "0-10%",
          "txns": 10845600
        },
        {
          "partition_0": "2025-07-24",
          "overspent_fee_bucket": "10-30%",
          "txns": 18076908
        },
        {
          "partition_0": "2025-07-27",
          "overspent_fee_bucket": "80-100%",
          "txns": 32800656
        },
        {
          "partition_0": "2025-08-01",
          "overspent_fee_bucket": "0%",
          "txns": 6656680
        },
        {
          "partition_0": "2025-08-06",
          "overspent_fee_bucket": "0%",
          "txns": 616891
        },
        {
          "partition_0": "2025-07-12",
          "overspent_fee_bucket": "80-100%",
          "txns": 36953429
        },
        {
          "partition_0": "2025-08-04",
          "overspent_fee_bucket": "10-30%",
          "txns": 2597489
        },
        {
          "partition_0": "2025-07-19",
          "overspent_fee_bucket": "30-50%",
          "txns": 8560239
        },
        {
          "partition_0": "2025-07-24",
          "overspent_fee_bucket": "0%",
          "txns": 5450446
        },
        {
          "partition_0": "2025-07-18",
          "overspent_fee_bucket": "10-30%",
          "txns": 20036290
        },
        {
          "partition_0": "2025-07-31",
          "overspent_fee_bucket": "30-50%",
          "txns": 9064156
        },
        {
          "partition_0": "2025-07-26",
          "overspent_fee_bucket": "30-50%",
          "txns": 8669219
        },
        {
          "partition_0": "2025-08-03",
          "overspent_fee_bucket": "10-30%",
          "txns": 2313592
        },
        {
          "partition_0": "2025-08-05",
          "overspent_fee_bucket": "0%",
          "txns": 577088
        },
        {
          "partition_0": "2025-08-06",
          "overspent_fee_bucket": "10-30%",
          "txns": 2399995
        },
        {
          "partition_0": "2025-07-22",
          "overspent_fee_bucket": "0-10%",
          "txns": 13250846
        },
        {
          "partition_0": "2025-07-29",
          "overspent_fee_bucket": "30-50%",
          "txns": 9466632
        },
        {
          "partition_0": "2025-07-26",
          "overspent_fee_bucket": "80-100%",
          "txns": 35439753
        },
        {
          "partition_0": "2025-07-23",
          "overspent_fee_bucket": "50-80%",
          "txns": 20408021
        },
        {
          "partition_0": "2025-07-18",
          "overspent_fee_bucket": "0%",
          "txns": 5047497
        },
        {
          "partition_0": "2025-07-15",
          "overspent_fee_bucket": "0%",
          "txns": 4495565
        },
        {
          "partition_0": "2025-07-16",
          "overspent_fee_bucket": "50-80%",
          "txns": 21926301
        },
        {
          "partition_0": "2025-07-20",
          "overspent_fee_bucket": "0%",
          "txns": 4388000
        },
        {
          "partition_0": "2025-07-25",
          "overspent_fee_bucket": "30-50%",
          "txns": 10070039
        },
        {
          "partition_0": "2025-08-02",
          "overspent_fee_bucket": "50-80%",
          "txns": 15256311
        },
        {
          "partition_0": "2025-07-25",
          "overspent_fee_bucket": "0%",
          "txns": 5579430
        },
        {
          "partition_0": "2025-07-23",
          "overspent_fee_bucket": "30-50%",
          "txns": 10463180
        },
        {
          "partition_0": "2025-08-04",
          "overspent_fee_bucket": "0%",
          "txns": 598383
        },
        {
          "partition_0": "2025-07-16",
          "overspent_fee_bucket": "0-10%",
          "txns": 11033754
        },
        {
          "partition_0": "2025-07-20",
          "overspent_fee_bucket": "30-50%",
          "txns": 9650060
        },
        {
          "partition_0": "2025-07-20",
          "overspent_fee_bucket": "50-80%",
          "txns": 19018320
        },
        {
          "partition_0": "2025-08-02",
          "overspent_fee_bucket": "30-50%",
          "txns": 6878544
        }
      ],
      "timestamp": 1754709646164,
      "chartId": "chart_1748203416425_8xpb11d",
      "title": "Cu Overspending"
    },
    {
      "success": true,
      "data": [
        {
          "overspent_fee_bucket": "0%",
          "txns": 123553678
        },
        {
          "overspent_fee_bucket": "0-10%",
          "txns": 253629094
        },
        {
          "overspent_fee_bucket": "10-30%",
          "txns": 449856732
        },
        {
          "overspent_fee_bucket": "30-50%",
          "txns": 251718243
        },
        {
          "overspent_fee_bucket": "50-80%",
          "txns": 550239147
        },
        {
          "overspent_fee_bucket": "80-100%",
          "txns": 1003667247
        }
      ],
      "timestamp": 1754709646144,
      "chartId": "chart_1748204829942_o15ujsb",
      "title": "Total Cu Overspending - Last 30 Days"
    },
    {
      "success": true,
      "data": [
        {
          "partition_0": "2025-07-23",
          "priorty_fee": 6343.055287458,
          "consumed_cu_fee_paid": 2919.182451224,
          "unused_cu_fee_paid": 2497.235074444,
          "priorty_fee_usd": 1223055.1136557546,
          "consumed_cu_fee_paid_usd": 562870.866303685,
          "unused_cu_fee_paid_usd": 481511.8250409018,
          "unused_cu_fee_paid_percentage": 39.369593378473844
        },
        {
          "partition_0": "2025-08-07",
          "priorty_fee": 1296.370171123,
          "consumed_cu_fee_paid": 411.089450964,
          "unused_cu_fee_paid": 552.809733777,
          "priorty_fee_usd": 221357.4560021065,
          "consumed_cu_fee_paid_usd": 70194.23701786167,
          "unused_cu_fee_paid_usd": 94393.22120168417,
          "unused_cu_fee_paid_percentage": 42.64289213767702
        },
        {
          "partition_0": "2025-07-31",
          "priorty_fee": 5663.450939596,
          "consumed_cu_fee_paid": 2791.43227969,
          "unused_cu_fee_paid": 2026.700029682,
          "priorty_fee_usd": 1004914.9699126194,
          "consumed_cu_fee_paid_usd": 495307.9165470612,
          "unused_cu_fee_paid_usd": 359614.8745830005,
          "unused_cu_fee_paid_percentage": 35.785602299692094
        },
        {
          "partition_0": "2025-07-20",
          "priorty_fee": 5268.293940423,
          "consumed_cu_fee_paid": 2424.485447126,
          "unused_cu_fee_paid": 1976.805602303,
          "priorty_fee_usd": 948150.781088915,
          "consumed_cu_fee_paid_usd": 436341.97264373815,
          "unused_cu_fee_paid_usd": 355771.6780954786,
          "unused_cu_fee_paid_percentage": 37.52268997625973
        },
        {
          "partition_0": "2025-07-29",
          "priorty_fee": 5570.741837089,
          "consumed_cu_fee_paid": 2590.680080233,
          "unused_cu_fee_paid": 2083.521946592,
          "priorty_fee_usd": 1015524.4551853037,
          "consumed_cu_fee_paid_usd": 472270.8490136776,
          "unused_cu_fee_paid_usd": 379817.9042497353,
          "unused_cu_fee_paid_percentage": 37.40115782641882
        },
        {
          "partition_0": "2025-08-02",
          "priorty_fee": 3457.759472699,
          "consumed_cu_fee_paid": 1626.359339937,
          "unused_cu_fee_paid": 1230.004951476,
          "priorty_fee_usd": 559513.2798091208,
          "consumed_cu_fee_paid_usd": 263167.42261024273,
          "unused_cu_fee_paid_usd": 199031.80369125228,
          "unused_cu_fee_paid_percentage": 35.57231094839293
        },
        {
          "partition_0": "2025-07-22",
          "priorty_fee": 7238.406208421,
          "consumed_cu_fee_paid": 3336.474609552,
          "unused_cu_fee_paid": 2797.7592357,
          "priorty_fee_usd": 1447966.4133227882,
          "consumed_cu_fee_paid_usd": 667426.3690693625,
          "unused_cu_fee_paid_usd": 559662.070518275,
          "unused_cu_fee_paid_percentage": 38.651592009925466
        },
        {
          "partition_0": "2025-08-06",
          "priorty_fee": 971.758524268,
          "consumed_cu_fee_paid": 313.733335809,
          "unused_cu_fee_paid": 399.344848347,
          "priorty_fee_usd": 160883.05398878801,
          "consumed_cu_fee_paid_usd": 51941.275473825066,
          "unused_cu_fee_paid_usd": 66115.0040800012,
          "unused_cu_fee_paid_percentage": 41.09507026427331
        },
        {
          "partition_0": "2025-07-30",
          "priorty_fee": 5978.447562582,
          "consumed_cu_fee_paid": 2738.741222251,
          "unused_cu_fee_paid": 2390.688126469,
          "priorty_fee_usd": 1065489.6226151332,
          "consumed_cu_fee_paid_usd": 488103.36141452147,
          "unused_cu_fee_paid_usd": 426072.7158676984,
          "unused_cu_fee_paid_percentage": 39.98844351218995
        },
        {
          "partition_0": "2025-07-19",
          "priorty_fee": 4747.650508388,
          "consumed_cu_fee_paid": 2282.443020715,
          "unused_cu_fee_paid": 1752.723689404,
          "priorty_fee_usd": 839201.1665043546,
          "consumed_cu_fee_paid_usd": 403447.73527024174,
          "unused_cu_fee_paid_usd": 309813.82519815525,
          "unused_cu_fee_paid_percentage": 36.91770669107473
        },
        {
          "partition_0": "2025-08-03",
          "priorty_fee": 3913.219216672,
          "consumed_cu_fee_paid": 1866.741968757,
          "unused_cu_fee_paid": 1399.352356143,
          "priorty_fee_usd": 629934.156730959,
          "consumed_cu_fee_paid_usd": 300500.5502664624,
          "unused_cu_fee_paid_usd": 225262.06624991825,
          "unused_cu_fee_paid_percentage": 35.759620881476714
        },
        {
          "partition_0": "2025-07-09",
          "priorty_fee": 6063.119927156,
          "consumed_cu_fee_paid": 2959.314934197,
          "unused_cu_fee_paid": 2214.042174945,
          "priorty_fee_usd": 935506.8777382801,
          "consumed_cu_fee_paid_usd": 456606.4184109728,
          "unused_cu_fee_paid_usd": 341614.8298480417,
          "unused_cu_fee_paid_percentage": 36.516549260861
        },
        {
          "partition_0": "2025-07-15",
          "priorty_fee": 7555.887300229,
          "consumed_cu_fee_paid": 3495.816369545,
          "unused_cu_fee_paid": 2807.249652059,
          "priorty_fee_usd": 1213052.5671052125,
          "consumed_cu_fee_paid_usd": 561232.4340883782,
          "unused_cu_fee_paid_usd": 450687.16110048076,
          "unused_cu_fee_paid_percentage": 37.15314350935222
        },
        {
          "partition_0": "2025-08-08",
          "priorty_fee": 1041.613939599,
          "consumed_cu_fee_paid": 303.06571148,
          "unused_cu_fee_paid": 489.288626418,
          "priorty_fee_usd": 183457.95247992885,
          "consumed_cu_fee_paid_usd": 53378.52421252969,
          "unused_cu_fee_paid_usd": 86177.6961327153,
          "unused_cu_fee_paid_percentage": 46.974085869700055
        },
        {
          "partition_0": "2025-07-11",
          "priorty_fee": 6033.885729544,
          "consumed_cu_fee_paid": 2957.821564789,
          "unused_cu_fee_paid": 2177.606784771,
          "priorty_fee_usd": 988826.2922494591,
          "consumed_cu_fee_paid_usd": 484724.41510204645,
          "unused_cu_fee_paid_usd": 356863.70930413756,
          "unused_cu_fee_paid_percentage": 36.089625862629134
        },
        {
          "partition_0": "2025-07-12",
          "priorty_fee": 4595.09707747,
          "consumed_cu_fee_paid": 2161.959312483,
          "unused_cu_fee_paid": 1732.100195863,
          "priorty_fee_usd": 739799.1169218194,
          "consumed_cu_fee_paid_usd": 348070.03273942677,
          "unused_cu_fee_paid_usd": 278863.7919321355,
          "unused_cu_fee_paid_percentage": 37.694528900283245
        },
        {
          "partition_0": "2025-07-27",
          "priorty_fee": 4079.295213945,
          "consumed_cu_fee_paid": 1833.733544368,
          "unused_cu_fee_paid": 1532.82109027,
          "priorty_fee_usd": 764537.7171950318,
          "consumed_cu_fee_paid_usd": 343676.6363862303,
          "unused_cu_fee_paid_usd": 287279.9039445116,
          "unused_cu_fee_paid_percentage": 37.57563524772803
        },
        {
          "partition_0": "2025-07-26",
          "priorty_fee": 4569.105188927,
          "consumed_cu_fee_paid": 2090.587637371,
          "unused_cu_fee_paid": 1751.600573597,
          "priorty_fee_usd": 853501.5843971132,
          "consumed_cu_fee_paid_usd": 390518.44661868946,
          "unused_cu_fee_paid_usd": 327196.20209641376,
          "unused_cu_fee_paid_percentage": 38.33574630415419
        },
        {
          "partition_0": "2025-08-05",
          "priorty_fee": 1082.417873932,
          "consumed_cu_fee_paid": 340.316825335,
          "unused_cu_fee_paid": 490.792210874,
          "priorty_fee_usd": 180141.82326072743,
          "consumed_cu_fee_paid_usd": 56637.362407414155,
          "unused_cu_fee_paid_usd": 81680.28802761623,
          "unused_cu_fee_paid_percentage": 45.342212346433655
        },
        {
          "partition_0": "2025-07-13",
          "priorty_fee": 4389.317133602,
          "consumed_cu_fee_paid": 2106.896858777,
          "unused_cu_fee_paid": 1550.749862684,
          "priorty_fee_usd": 710960.4159181007,
          "consumed_cu_fee_paid_usd": 341264.9898421442,
          "unused_cu_fee_paid_usd": 251182.98218155708,
          "unused_cu_fee_paid_percentage": 35.33009385018872
        },
        {
          "partition_0": "2025-07-10",
          "priorty_fee": 6996.520012714,
          "consumed_cu_fee_paid": 3325.475656816,
          "unused_cu_fee_paid": 2615.113770949,
          "priorty_fee_usd": 1116734.434754207,
          "consumed_cu_fee_paid_usd": 530788.616505755,
          "unused_cu_fee_paid_usd": 417405.73792567983,
          "unused_cu_fee_paid_percentage": 37.3773499710834
        },
        {
          "partition_0": "2025-07-16",
          "priorty_fee": 9144.345307301,
          "consumed_cu_fee_paid": 4404.096725514,
          "unused_cu_fee_paid": 3401.722752362,
          "priorty_fee_usd": 1540134.9999576102,
          "consumed_cu_fee_paid_usd": 741759.3367506836,
          "unused_cu_fee_paid_usd": 572934.6492287265,
          "unused_cu_fee_paid_percentage": 37.2002875880683
        },
        {
          "partition_0": "2025-07-14",
          "priorty_fee": 7178.180305909,
          "consumed_cu_fee_paid": 3399.302320086,
          "unused_cu_fee_paid": 2537.383375112,
          "priorty_fee_usd": 1186006.6370778885,
          "consumed_cu_fee_paid_usd": 561645.8407623859,
          "unused_cu_fee_paid_usd": 419236.2681690593,
          "unused_cu_fee_paid_percentage": 35.34856003858323
        },
        {
          "partition_0": "2025-07-25",
          "priorty_fee": 5287.425894204,
          "consumed_cu_fee_paid": 2377.949967772,
          "unused_cu_fee_paid": 2025.436569518,
          "priorty_fee_usd": 951423.376638936,
          "consumed_cu_fee_paid_usd": 427890.09871441155,
          "unused_cu_fee_paid_usd": 364458.57373645663,
          "unused_cu_fee_paid_percentage": 38.30666585300523
        },
        {
          "partition_0": "2025-08-04",
          "priorty_fee": 914.916603315,
          "consumed_cu_fee_paid": 292.580964571,
          "unused_cu_fee_paid": 397.544147946,
          "priorty_fee_usd": 151482.0175890528,
          "consumed_cu_fee_paid_usd": 48442.39864134032,
          "unused_cu_fee_paid_usd": 65821.06980394074,
          "unused_cu_fee_paid_percentage": 43.45140819453771
        },
        {
          "partition_0": "2025-07-21",
          "priorty_fee": 6788.880822229,
          "consumed_cu_fee_paid": 3167.596421293,
          "unused_cu_fee_paid": 2625.525743885,
          "priorty_fee_usd": 1293235.077183497,
          "consumed_cu_fee_paid_usd": 603405.3196167364,
          "unused_cu_fee_paid_usd": 500144.58597102814,
          "unused_cu_fee_paid_percentage": 38.67391124746477
        },
        {
          "partition_0": "2025-08-01",
          "priorty_fee": 5245.936850796,
          "consumed_cu_fee_paid": 2260.840598389,
          "unused_cu_fee_paid": 2215.342010845,
          "priorty_fee_usd": 877762.6102469666,
          "consumed_cu_fee_paid_usd": 378289.21724307915,
          "unused_cu_fee_paid_usd": 370676.285539734,
          "unused_cu_fee_paid_percentage": 42.22967362843592
        },
        {
          "partition_0": "2025-07-17",
          "priorty_fee": 8812.058047508,
          "consumed_cu_fee_paid": 4104.2519968,
          "unused_cu_fee_paid": 3254.257403553,
          "priorty_fee_usd": 1533866.6385449974,
          "consumed_cu_fee_paid_usd": 714404.6464666112,
          "unused_cu_fee_paid_usd": 566450.747105508,
          "unused_cu_fee_paid_percentage": 36.92959562917638
        },
        {
          "partition_0": "2025-07-18",
          "priorty_fee": 8843.574748839,
          "consumed_cu_fee_paid": 4136.247277697,
          "unused_cu_fee_paid": 3304.584465081,
          "priorty_fee_usd": 1578873.2852136462,
          "consumed_cu_fee_paid_usd": 738458.2042064847,
          "unused_cu_fee_paid_usd": 589978.6318121394,
          "unused_cu_fee_paid_percentage": 37.36706658712679
        },
        {
          "partition_0": "2025-07-28",
          "priorty_fee": 5913.334580239,
          "consumed_cu_fee_paid": 2657.924733784,
          "unused_cu_fee_paid": 2280.714403819,
          "priorty_fee_usd": 1116136.8015676055,
          "consumed_cu_fee_paid_usd": 501681.0009511083,
          "unused_cu_fee_paid_usd": 430482.87652697327,
          "unused_cu_fee_paid_percentage": 38.56900658793469
        },
        {
          "partition_0": "2025-07-24",
          "priorty_fee": 6882.028163917,
          "consumed_cu_fee_paid": 3158.507440713,
          "unused_cu_fee_paid": 2714.138392168,
          "priorty_fee_usd": 1283001.137955603,
          "consumed_cu_fee_paid_usd": 588833.4868960428,
          "unused_cu_fee_paid_usd": 505990.7577795452,
          "unused_cu_fee_paid_percentage": 39.438059937017336
        }
      ],
      "timestamp": 1754709646174,
      "chartId": "chart_1748205678451_hrbbfn8",
      "title": "Priority Fee Breakdown"
    }
  ],
  "summary": {
    "totalCharts": 3,
    "successfulFetches": 3,
    "failedFetches": 0
  }
}