{
  "pageId": "dex-token-hotspots",
  "pageName": "DEX & Token Hotspots",
  "fetchedAt": "2025-07-07T08:27:42.433Z",
  "charts": [
    {
      "success": true,
      "data": [
        {
          "token": "GOR",
          "attacks": 693,
          "total_sol_drained": 163.63945152800025
        },
        {
          "token": "ONE",
          "attacks": 353,
          "total_sol_drained": 84.15383101500001
        },
        {
          "token": "USDP",
          "attacks": 361,
          "total_sol_drained": 71.089074451
        },
        {
          "token": "solami",
          "attacks": 341,
          "total_sol_drained": 56.04025662500005
        },
        {
          "token": "CryBB",
          "attacks": 170,
          "total_sol_drained": 55.54456507100004
        },
        {
          "token": "shiyo",
          "attacks": 192,
          "total_sol_drained": 55.35468894200008
        },
        {
          "token": "VERSE",
          "attacks": 122,
          "total_sol_drained": 50.177309511000004
        },
        {
          "token": "BUNKER",
          "attacks": 65,
          "total_sol_drained": 47.00098191899996
        },
        {
          "token": "T1DW",
          "attacks": 140,
          "total_sol_drained": 46.96383094199996
        },
        {
          "token": "EURA",
          "attacks": 9,
          "total_sol_drained": 42.836309593999985
        }
      ],
      "timestamp": 1751876861658,
      "chartId": "chart_1747914341226_ps3utjg",
      "title": "Top tokens attacked - by SOL drained"
    },
    {
      "success": true,
      "data": [
        {
          "token": "GOR",
          "attacks": 693,
          "total_sol_drained": 163.63945152800025
        },
        {
          "token": "ONE",
          "attacks": 353,
          "total_sol_drained": 84.15383101500001
        },
        {
          "token": "USDP",
          "attacks": 361,
          "total_sol_drained": 71.089074451
        },
        {
          "token": "solami",
          "attacks": 341,
          "total_sol_drained": 56.04025662500005
        },
        {
          "token": "CryBB",
          "attacks": 170,
          "total_sol_drained": 55.54456507100004
        },
        {
          "token": "shiyo",
          "attacks": 192,
          "total_sol_drained": 55.35468894200008
        },
        {
          "token": "VERSE",
          "attacks": 122,
          "total_sol_drained": 50.177309511000004
        },
        {
          "token": "BUNKER",
          "attacks": 65,
          "total_sol_drained": 47.00098191899996
        },
        {
          "token": "T1DW",
          "attacks": 140,
          "total_sol_drained": 46.96383094199996
        },
        {
          "token": "EURA",
          "attacks": 9,
          "total_sol_drained": 42.836309593999985
        }
      ],
      "timestamp": 1751876861661,
      "chartId": "chart_1747936232766_dnjy7l0",
      "title": "Top tokens attacked - by attacks"
    },
    {
      "success": true,
      "data": [
        {
          "dex": "Pump.fun AMM",
          "attacks": 105668,
          "total_sol_drained": 8306.795029530998
        },
        {
          "dex": "Pump AMM",
          "attacks": 105668,
          "total_sol_drained": 8306.795029530998
        },
        {
          "dex": "PUMP FUN",
          "attacks": 57741,
          "total_sol_drained": 7289.254239010997
        },
        {
          "dex": "Raydium CPMM",
          "attacks": 12120,
          "total_sol_drained": 2101.9977473189997
        },
        {
          "dex": "Raydium V4",
          "attacks": 25141,
          "total_sol_drained": 1872.8567660160008
        },
        {
          "dex": "LanMV9sAd7wArD4vJFi2qDdfnVhFxYSUg6eADduJ3uj",
          "attacks": 2087,
          "total_sol_drained": 636.9256565959998
        },
        {
          "dex": "cpamdpZCGKUy5JxQXB4dcpGPiikHawvSWAd6mEn1sGG",
          "attacks": 286,
          "total_sol_drained": 158.27223855500006
        }
      ],
      "timestamp": 1751876861674,
      "chartId": "chart_1747936484816_kqdflfn",
      "title": "Top DEXs used - by SOL drained"
    },
    {
      "success": true,
      "data": [
        {
          "dex": "Pump.fun AMM",
          "attacks": 105668,
          "total_sol_drained": 8306.795029530998
        },
        {
          "dex": "Pump AMM",
          "attacks": 105668,
          "total_sol_drained": 8306.795029530998
        },
        {
          "dex": "PUMP FUN",
          "attacks": 57741,
          "total_sol_drained": 7289.254239010997
        },
        {
          "dex": "Raydium CPMM",
          "attacks": 12120,
          "total_sol_drained": 2101.9977473189997
        },
        {
          "dex": "Raydium V4",
          "attacks": 25141,
          "total_sol_drained": 1872.8567660160008
        },
        {
          "dex": "LanMV9sAd7wArD4vJFi2qDdfnVhFxYSUg6eADduJ3uj",
          "attacks": 2087,
          "total_sol_drained": 636.9256565959998
        },
        {
          "dex": "cpamdpZCGKUy5JxQXB4dcpGPiikHawvSWAd6mEn1sGG",
          "attacks": 286,
          "total_sol_drained": 158.27223855500006
        }
      ],
      "timestamp": 1751876862433,
      "chartId": "chart_1747936861655_4nzbmez",
      "title": "Top DEXs used - by attacks"
    }
  ],
  "summary": {
    "totalCharts": 4,
    "successfulFetches": 4,
    "failedFetches": 0
  }
}